{
  "fetched_at": "2026-01-05T04:59:54Z",
  "lat": 53.64,
  "lon": 8.01,
  "extremes": [
    {
      "dt": 1767571200,
      "type": "High",
      "height": 1.817
    },
    {
      "dt": 1767595080,
      "type": "Low",
      "height": -2.007
    },
    {
      "dt": 1767616620,
      "type": "High",
      "height": 1.549
    },
    {
      "dt": 1767639240,
      "type": "Low",
      "height": -1.804
    },
    {
      "dt": 1767660720,
      "type": "High",
      "height": 1.851
    },
    {
      "dt": 1767684360,
      "type": "Low",
      "height": -2.027
    },
    {
      "dt": 1767706080,
      "type": "High",
      "height": 1.488
    },
    {
      "dt": 1767728340,
      "type": "Low",
      "height": -1.805
    },
    {
      "dt": 1767750000,
      "type": "High",
      "height": 1.855
    },
    {
      "dt": 1767773520,
      "type": "Low",
      "height": -1.989
    },
    {
      "dt": 1767795240,
      "type": "High",
      "height": 1.427
    },
    {
      "dt": 1767817320,
      "type": "Low",
      "height": -1.771
    },
    {
      "dt": 1767839100,
      "type": "High",
      "height": 1.829
    },
    {
      "dt": 1767862440,
      "type": "Low",
      "height": -1.895
    },
    {
      "dt": 1767884160,
      "type": "High",
      "height": 1.368
    },
    {
      "dt": 1767906180,
      "type": "Low",
      "height": -1.699
    },
    {
      "dt": 1767928020,
      "type": "High",
      "height": 1.769
    },
    {
      "dt": 1767951300,
      "type": "Low",
      "height": -1.755
    },
    {
      "dt": 1767972960,
      "type": "High",
      "height": 1.311
    },
    {
      "dt": 1767994980,
      "type": "Low",
      "height": -1.588
    },
    {
      "dt": 1768016940,
      "type": "High",
      "height": 1.677
    },
    {
      "dt": 1768040160,
      "type": "Low",
      "height": -1.588
    },
    {
      "dt": 1768061880,
      "type": "High",
      "height": 1.259
    },
    {
      "dt": 1768083900,
      "type": "Low",
      "height": -1.45
    },
    {
      "dt": 1768106040,
      "type": "High",
      "height": 1.563
    },
    {
      "dt": 1768129200,
      "type": "Low",
      "height": -1.416
    },
    {
      "dt": 1768151100,
      "type": "High",
      "height": 1.217
    }
  ]
}