{
  "fetched_at": "2025-11-15T04:40:59Z",
  "lat": 53.64,
  "lon": 8.01,
  "current": {
    "temp": 6.2,
    "feels_like": -0.2,
    "humidity": 85,
    "wind_speed": 9.6,
    "wind_deg": 88,
    "weather": [
      {
        "icon": "10d",
        "description": "Regen leicht"
      }
    ],
    "dt": 1763181659
  },
  "hourly": [
    {
      "dt": 1763164800,
      "temp": 6.7,
      "wind_speed": 8.69,
      "weather": [
        {
          "icon": "10d",
          "description": "Regen leicht"
        }
      ]
    },
    {
      "dt": 1763168400,
      "temp": 6.6,
      "wind_speed": 7.3,
      "weather": [
        {
          "icon": "10d",
          "description": "Regen leicht"
        }
      ]
    },
    {
      "dt": 1763172000,
      "temp": 6.6,
      "wind_speed": 8.22,
      "weather": [
        {
          "icon": "10d",
          "description": "Regen leicht"
        }
      ]
    },
    {
      "dt": 1763175600,
      "temp": 6.6,
      "wind_speed": 9.36,
      "weather": [
        {
          "icon": "10d",
          "description": "Regen leicht"
        }
      ]
    },
    {
      "dt": 1763179200,
      "temp": 6.4,
      "wind_speed": 9.3,
      "weather": [
        {
          "icon": "10d",
          "description": "Regen leicht"
        }
      ]
    },
    {
      "dt": 1763182800,
      "temp": 6.3,
      "wind_speed": 9.53,
      "weather": [
        {
          "icon": "10d",
          "description": "Regen leicht"
        }
      ]
    },
    {
      "dt": 1763186400,
      "temp": 6.2,
      "wind_speed": 9.7,
      "weather": [
        {
          "icon": "04d",
          "description": "bedeckt"
        }
      ]
    },
    {
      "dt": 1763190000,
      "temp": 6.3,
      "wind_speed": 8.95,
      "weather": [
        {
          "icon": "10d",
          "description": "Regen leicht"
        }
      ]
    },
    {
      "dt": 1763193600,
      "temp": 6.5,
      "wind_speed": 8.73,
      "weather": [
        {
          "icon": "10d",
          "description": "Regen leicht"
        }
      ]
    },
    {
      "dt": 1763197200,
      "temp": 6.7,
      "wind_speed": 9.21,
      "weather": [
        {
          "icon": "10d",
          "description": "Regen leicht"
        }
      ]
    },
    {
      "dt": 1763200800,
      "temp": 6.7,
      "wind_speed": 9.11,
      "weather": [
        {
          "icon": "10d",
          "description": "Regen leicht"
        }
      ]
    },
    {
      "dt": 1763204400,
      "temp": 6.9,
      "wind_speed": 9.01,
      "weather": [
        {
          "icon": "10d",
          "description": "Regen leicht"
        }
      ]
    },
    {
      "dt": 1763208000,
      "temp": 7.1,
      "wind_speed": 9.02,
      "weather": [
        {
          "icon": "04d",
          "description": "bedeckt"
        }
      ]
    },
    {
      "dt": 1763211600,
      "temp": 7.1,
      "wind_speed": 9.51,
      "weather": [
        {
          "icon": "04d",
          "description": "bedeckt"
        }
      ]
    },
    {
      "dt": 1763215200,
      "temp": 7.2,
      "wind_speed": 9.6,
      "weather": [
        {
          "icon": "04d",
          "description": "bedeckt"
        }
      ]
    },
    {
      "dt": 1763218800,
      "temp": 7.1,
      "wind_speed": 9.6,
      "weather": [
        {
          "icon": "04d",
          "description": "bedeckt"
        }
      ]
    },
    {
      "dt": 1763222400,
      "temp": 6.9,
      "wind_speed": 8.62,
      "weather": [
        {
          "icon": "04d",
          "description": "bedeckt"
        }
      ]
    },
    {
      "dt": 1763226000,
      "temp": 6.7,
      "wind_speed": 8.81,
      "weather": [
        {
          "icon": "10d",
          "description": "Regen leicht"
        }
      ]
    },
    {
      "dt": 1763229600,
      "temp": 6.5,
      "wind_speed": 8.8,
      "weather": [
        {
          "icon": "04d",
          "description": "bedeckt"
        }
      ]
    },
    {
      "dt": 1763233200,
      "temp": 6.4,
      "wind_speed": 8.1,
      "weather": [
        {
          "icon": "10d",
          "description": "Regen leicht"
        }
      ]
    },
    {
      "dt": 1763236800,
      "temp": 6.2,
      "wind_speed": 7.62,
      "weather": [
        {
          "icon": "10d",
          "description": "Regen leicht"
        }
      ]
    },
    {
      "dt": 1763240400,
      "temp": 6.0,
      "wind_speed": 7.21,
      "weather": [
        {
          "icon": "10d",
          "description": "Regen leicht"
        }
      ]
    },
    {
      "dt": 1763244000,
      "temp": 6.0,
      "wind_speed": 6.94,
      "weather": [
        {
          "icon": "04d",
          "description": "bedeckt"
        }
      ]
    },
    {
      "dt": 1763247600,
      "temp": 5.9,
      "wind_speed": 6.51,
      "weather": [
        {
          "icon": "09d",
          "description": "Nieselregen leicht"
        }
      ]
    }
  ],
  "daily": [
    {
      "dt": 1763208000,
      "sunrise": 1763193240,
      "sunset": 1763224200,
      "temp": {
        "min": 5.9,
        "max": 7.2
      },
      "weather": [
        {
          "icon": "10d",
          "description": "Regen leicht"
        }
      ]
    },
    {
      "dt": 1763294400,
      "sunrise": 1763279760,
      "sunset": 1763310480,
      "temp": {
        "min": 4.5,
        "max": 6.9
      },
      "weather": [
        {
          "icon": "10d",
          "description": "Regen leicht"
        }
      ]
    },
    {
      "dt": 1763380800,
      "sunrise": 1763366280,
      "sunset": 1763396820,
      "temp": {
        "min": 4.5,
        "max": 7.2
      },
      "weather": [
        {
          "icon": "09d",
          "description": "Regenschauer leicht"
        }
      ]
    },
    {
      "dt": 1763467200,
      "sunrise": 1763452800,
      "sunset": 1763483100,
      "temp": {
        "min": 4.1,
        "max": 6.4
      },
      "weather": [
        {
          "icon": "09d",
          "description": "Regenschauer leicht"
        }
      ]
    },
    {
      "dt": 1763553600,
      "sunrise": 1763539320,
      "sunset": 1763569440,
      "temp": {
        "min": 1.6,
        "max": 5.1
      },
      "weather": [
        {
          "icon": "10d",
          "description": "Regen leicht"
        }
      ]
    },
    {
      "dt": 1763640000,
      "sunrise": 1763625840,
      "sunset": 1763655780,
      "temp": {
        "min": 1.3,
        "max": 4.0
      },
      "weather": [
        {
          "icon": "10d",
          "description": "Regen leicht"
        }
      ]
    },
    {
      "dt": 1763726400,
      "sunrise": 1763712300,
      "sunset": 1763742060,
      "temp": {
        "min": 1.2,
        "max": 5.3
      },
      "weather": [
        {
          "icon": "50d",
          "description": "Nebel"
        }
      ]
    }
  ]
}